{
  "stories": [
    {
      "id": 1,
      "title": "첫 번째 이야기",
      "body": "Remix..."
    },
    {
      "id": 2,
      "title": "두 번째 이야기",
      "body": "Data Loading...!"
    },
    {
      "id": 3,
      "title": "세 번째 이야기",
      "body": "Data Write!!!"
    },
    {
      "title": "김태형 이야기",
      "body": "김태형 이야기입니다.",
      "id": 4
    },
    {
      "title": "레프 이야기",
      "body": "레프 이야기입니다",
      "id": 5
    },
    {
      "title": "헬로",
      "body": "안녕",
      "id": 6
    }
  ]
}